{
  "id": "",
  "name": "",
  "font_family": "iconfont",
  "css_prefix_text": "icon-",
  "description": "",
  "glyphs": [
    {
      "icon_id": "287191",
      "name": "收藏",
      "font_class": "shoucang",
      "unicode": "e63a",
      "unicode_decimal": 58938
    },
    {
      "icon_id": "706797",
      "name": "足球",
      "font_class": "zuqiu-copy",
      "unicode": "e619",
      "unicode_decimal": 58905
    },
    {
      "icon_id": "925483",
      "name": "密码",
      "font_class": "mima",
      "unicode": "e64c",
      "unicode_decimal": 58956
    },
    {
      "icon_id": "942962",
      "name": "返回顶部",
      "font_class": "icon3",
      "unicode": "e67f",
      "unicode_decimal": 59007
    },
    {
      "icon_id": "4023193",
      "name": "修改",
      "font_class": "modify",
      "unicode": "e68e",
      "unicode_decimal": 59022
    },
    {
      "icon_id": "4485675",
      "name": "邮箱",
      "font_class": "youxiang",
      "unicode": "e533",
      "unicode_decimal": 58675
    },
    {
      "icon_id": "5169490",
      "name": "棒球",
      "font_class": "bangqiu",
      "unicode": "e629",
      "unicode_decimal": 58921
    },
    {
      "icon_id": "5171979",
      "name": "篮球",
      "font_class": "lanqiu",
      "unicode": "e60e",
      "unicode_decimal": 58894
    },
    {
      "icon_id": "11794986",
      "name": "网球",
      "font_class": "wangqiu",
      "unicode": "e725",
      "unicode_decimal": 59173
    },
    {
      "icon_id": "15859083",
      "name": "手机",
      "font_class": "shouji",
      "unicode": "e602",
      "unicode_decimal": 58882
    }
  ]
}
